swift_sarsa.cpython-310-x86_64-linux-gnu.so
swiftsarsa/__init__.py
swiftsarsa/_version.py
swiftsarsa/libSwiftSarsa.a
swiftsarsa/include/SwiftSarsa.h
swiftsarsa-0.1.6.dist-info/METADATA
swiftsarsa-0.1.6.dist-info/WHEEL
swiftsarsa-0.1.6.dist-info/RECORD
