Metadata-Version: 2.2
Name: swiftsarsa
Version: 0.1.6
Summary: SwiftSarsa: Fast and Robust Linear Control
Author: Khurram Javed
License: MIT
Classifier: Development Status :: 4 - Beta
Classifier: Intended Audience :: Developers
Classifier: Intended Audience :: Science/Research
Classifier: License :: OSI Approved :: MIT License
Classifier: Operating System :: OS Independent
Classifier: Programming Language :: Python :: 3
Classifier: Programming Language :: Python :: 3.9
Classifier: Programming Language :: Python :: 3.10
Classifier: Programming Language :: Python :: 3.11
Classifier: Programming Language :: Python :: 3.12
Classifier: Programming Language :: Python :: 3.13
Classifier: Programming Language :: Python :: 3.14
Classifier: Programming Language :: C++
Classifier: Topic :: Scientific/Engineering
Classifier: Topic :: Software Development :: Libraries :: Python Modules
Project-URL: Homepage, https://github.com/khurramjaved96/swift-sarsa
Requires-Python: >=3.9
